README.md
setup.py
longview/__init__.py
longview/evaler.py
longview/lv_types.py
longview/renderers.py
longview/utils.py
longview/watch_client.py
longview/watch_server.py
longview/zmq_pub_sub.py
longview.egg-info/PKG-INFO
longview.egg-info/SOURCES.txt
longview.egg-info/dependency_links.txt
longview.egg-info/requires.txt
longview.egg-info/top_level.txt